encprox/__init__.py
encprox/encprox.py
encprox-1.5.2.dist-info/LICENSE
encprox-1.5.2.dist-info/METADATA
encprox-1.5.2.dist-info/WHEEL
encprox-1.5.2.dist-info/top_level.txt
encprox-1.5.2.dist-info/RECORD
