Metadata-Version: 2.1
Name: encprox
Version: 1.5.2
Summary: A simple python library to format private or public proxies.
Home-page: https://github.com/jiroawesome/encprox
Author: JiroDeveloper
Author-email: contact@jiroawesome.tech
License: MIT License
Keywords: proxy proxy-encode
Classifier: Programming Language :: Python
Classifier: Programming Language :: Python :: 2
Classifier: Programming Language :: Python :: 2.7
Classifier: Programming Language :: Python :: 3
Classifier: Programming Language :: Python :: 3.5
Classifier: Programming Language :: Python :: 3.6
Classifier: Programming Language :: Python :: 3.7
Classifier: Programming Language :: Python :: 3.8
Classifier: Programming Language :: Python :: 3.9
Classifier: Programming Language :: Python :: 3.10
License-File: LICENSE
